dydx_v4_client/__init__.py
dydx_v4_client/_bootstrap.py
dydx_v4_client/config.py
dydx_v4_client/faucet_client.py
dydx_v4_client/indexer/__init__.py
dydx_v4_client/indexer/candles_resolution.py
dydx_v4_client/indexer/rest/__init__.py
dydx_v4_client/indexer/rest/constants.py
dydx_v4_client/indexer/rest/indexer_client.py
dydx_v4_client/indexer/rest/modules/__init__.py
dydx_v4_client/indexer/rest/modules/account.py
dydx_v4_client/indexer/rest/modules/affiliate.py
dydx_v4_client/indexer/rest/modules/markets.py
dydx_v4_client/indexer/rest/modules/status.py
dydx_v4_client/indexer/rest/modules/vaults.py
dydx_v4_client/indexer/rest/noble_client.py
dydx_v4_client/indexer/rest/shared/__init__.py
dydx_v4_client/indexer/rest/shared/rest.py
dydx_v4_client/indexer/rest/utils/__init__.py
dydx_v4_client/indexer/rest/utils/request_helpers.py
dydx_v4_client/indexer/socket/__init__.py
dydx_v4_client/indexer/socket/websocket.py
dydx_v4_client/key_pair.py
dydx_v4_client/network.py
dydx_v4_client/node/__init__.py
dydx_v4_client/node/authenticators.py
dydx_v4_client/node/builder.py
dydx_v4_client/node/chain_helpers.py
dydx_v4_client/node/client.py
dydx_v4_client/node/fee.py
dydx_v4_client/node/market.py
dydx_v4_client/node/mega_vault.py
dydx_v4_client/node/message.py
dydx_v4_client/utility.py
dydx_v4_client/wallet.py
dydx_v4_client-1.1.5.post1.dist-info/METADATA
dydx_v4_client-1.1.5.post1.dist-info/WHEEL
dydx_v4_client-1.1.5.post1.dist-info/RECORD
