Metadata-Version: 2.4
Name: dydx-v4-client
Version: 1.1.5.post1
Summary: 
Author: Saul Martin
Author-email: saulmartin1@pm.me
Requires-Python: >=3.9,<4.0
Classifier: Programming Language :: Python :: 3
Classifier: Programming Language :: Python :: 3.9
Classifier: Programming Language :: Python :: 3.10
Classifier: Programming Language :: Python :: 3.11
Classifier: Programming Language :: Python :: 3.12
Classifier: Programming Language :: Python :: 3.13
Classifier: Programming Language :: Python :: 3.14
Requires-Dist: bech32 (>=1.2.0,<2.0.0)
Requires-Dist: bip-utils (>=2.9.3,<3.0.0)
Requires-Dist: coincurve (>=20.0.0,<21.0.0)
Requires-Dist: grpcio (>=1.68.0,<2.0.0)
Requires-Dist: httpx (>=0.27.0,<0.28.0)
Requires-Dist: pycryptodome (>=3.20.0,<4.0.0)
Requires-Dist: typing-extensions (>=4.12.2,<5.0.0)
Requires-Dist: v4-proto (>=8.2.0,<9.0.0)
Requires-Dist: websocket-client (>=1.7.0,<2.0.0)
